sgr.py
sgr-0.0.4.dist-info/METADATA
sgr-0.0.4.dist-info/WHEEL
sgr-0.0.4.dist-info/top_level.txt
sgr-0.0.4.dist-info/RECORD
