Metadata-Version: 2.1
Name: sgr
Version: 0.0.4
Summary: SageMaker Registry
Home-page: https://github.com/felixgao/sgr.git
Author: Felix Gao
License: http://www.apache.org/licenses/LICENSE-2.0
Platform: UNKNOWN
